{
	"tags"      : {
		"allowUnknownTags" : true
	},
	"plugins"   : ["plugins/markdown"],
	"source": {
        "excludePattern": "(^|\\/|\\\\)__"
    },
	"templates" : {
		"systemName"            : "@genx/model",
		"footer"                : "",
		"copyright"             : "Copyright (c) since 2018, Gen-X Tech Pty Ltd",
		"includeDate"           : false,
		"navType"               : "vertical",
		"theme"                 : "cerulean",
		"linenums"              : true,
		"collapseSymbols"       : false,
		"inverseNav"            : true,
		"outputSourceFiles"     : false,
		"outputSourcePath"      : true,
		"cleverLinks"		    : true
	},
	"markdown"  : {
		"parser"   : "gfm",
		"hardwrap" : true
	}
}
